<?xml version="1.0" encoding="UTF-8" standalone="yes"?><p:sld xmlns:a="http://schemas.openxmlformats.org/drawingml/2006/main" xmlns:r="http://schemas.openxmlformats.org/officeDocument/2006/relationships" xmlns:mc="http://schemas.openxmlformats.org/markup-compatibility/2006" xmlns:mv="urn:schemas-microsoft-com:mac:vml" xmlns:p="http://schemas.openxmlformats.org/presentationml/2006/main" xmlns:c="http://schemas.openxmlformats.org/drawingml/2006/chart" xmlns:dgm="http://schemas.openxmlformats.org/drawingml/2006/diagram" xmlns:o="urn:schemas-microsoft-com:office:office" xmlns:v="urn:schemas-microsoft-com:vml" xmlns:pvml="urn:schemas-microsoft-com:office:powerpoint" xmlns:com="http://schemas.openxmlformats.org/drawingml/2006/compatibility" xmlns:p14="http://schemas.microsoft.com/office/powerpoint/2010/main" xmlns:p15="http://schemas.microsoft.com/office/powerpoint/2012/main" xmlns:ahyp="http://schemas.microsoft.com/office/drawing/2018/hyperlinkcolor"><p:cSld><p:bg><p:bgPr><a:solidFill><a:srgbClr val="FFFFFF"/></a:solidFill></p:bgPr></p:bg><p:spTree><p:nvGrpSpPr><p:cNvPr id="474" name="Shape 474"/><p:cNvGrpSpPr/><p:nvPr/></p:nvGrpSpPr><p:grpSpPr><a:xfrm><a:off x="0" y="0"/><a:ext cx="0" cy="0"/><a:chOff x="0" y="0"/><a:chExt cx="0" cy="0"/></a:xfrm></p:grpSpPr><p:sp><p:nvSpPr><p:cNvPr id="475" name="Google Shape;475;p79"/><p:cNvSpPr txBox="1"/><p:nvPr><p:ph idx="4294967295" type="ctrTitle"/></p:nvPr></p:nvSpPr><p:spPr><a:xfrm><a:off x="4659100" y="0"/><a:ext cx="4485000" cy="5143500"/></a:xfrm><a:prstGeom prst="rect"><a:avLst/></a:prstGeom><a:gradFill><a:gsLst><a:gs pos="0"><a:srgbClr val="FFFFFF"/></a:gs><a:gs pos="50000"><a:srgbClr val="FAFAFA"/></a:gs><a:gs pos="100000"><a:srgbClr val="FFFFFF"/></a:gs></a:gsLst><a:path path="circle"><a:fillToRect b="50%" l="50%" r="50%" t="50%"/></a:path><a:tileRect/></a:gradFill></p:spPr><p:txBody><a:bodyPr anchorCtr="0" anchor="t" bIns="91425" lIns="91425" spcFirstLastPara="1" rIns="91425" wrap="square" tIns="91425"><a:noAutofit/></a:bodyPr><a:lstStyle/><a:p><a:pPr indent="0" lvl="0" marL="0" rtl="0" algn="l"><a:spcBef><a:spcPts val="0"/></a:spcBef><a:spcAft><a:spcPts val="0"/></a:spcAft><a:buNone/></a:pPr><a:r><a:rPr lang="en" sz="600"><a:solidFill><a:srgbClr val="FFFFFF"/></a:solidFill><a:latin typeface="Quicksand"/><a:ea typeface="Quicksand"/><a:cs typeface="Quicksand"/><a:sym typeface="Quicksand"/></a:rPr><a:t>.</a:t></a:r><a:endParaRPr sz="600"><a:solidFill><a:srgbClr val="FFFFFF"/></a:solidFill><a:latin typeface="Quicksand"/><a:ea typeface="Quicksand"/><a:cs typeface="Quicksand"/><a:sym typeface="Quicksand"/></a:endParaRPr></a:p></p:txBody></p:sp><p:sp><p:nvSpPr><p:cNvPr id="476" name="Google Shape;476;p79"/><p:cNvSpPr txBox="1"/><p:nvPr/></p:nvSpPr><p:spPr><a:xfrm><a:off x="0" y="50"/><a:ext cx="4659000" cy="5143500"/></a:xfrm><a:prstGeom prst="rect"><a:avLst/></a:prstGeom><a:gradFill><a:gsLst><a:gs pos="0"><a:srgbClr val="696969"/></a:gs><a:gs pos="100000"><a:srgbClr val="1D1D1D"/></a:gs></a:gsLst><a:path path="circle"><a:fillToRect b="50%" l="50%" r="50%" t="50%"/></a:path><a:tileRect/></a:gradFill><a:ln><a:noFill/></a:ln></p:spPr><p:txBody><a:bodyPr anchorCtr="0" anchor="t" bIns="91425" lIns="91425" spcFirstLastPara="1" rIns="91425" wrap="square" tIns="91425"><a:noAutofit/></a:bodyPr><a:lstStyle/><a:p><a:pPr indent="0" lvl="0" marL="0" rtl="0" algn="ctr"><a:spcBef><a:spcPts val="0"/></a:spcBef><a:spcAft><a:spcPts val="0"/></a:spcAft><a:buNone/></a:pPr><a:r><a:t></a:t></a:r><a:endParaRPr sz="3000"><a:solidFill><a:srgbClr val="F3F3F3"/></a:solidFill><a:latin typeface="Special Elite"/><a:ea typeface="Special Elite"/><a:cs typeface="Special Elite"/><a:sym typeface="Special Elite"/></a:endParaRPr></a:p></p:txBody></p:sp><p:sp><p:nvSpPr><p:cNvPr id="477" name="Google Shape;477;p79"/><p:cNvSpPr txBox="1"/><p:nvPr/></p:nvSpPr><p:spPr><a:xfrm><a:off x="0" y="-11475"/><a:ext cx="4659000" cy="678000"/></a:xfrm><a:prstGeom prst="rect"><a:avLst/></a:prstGeom><a:noFill/><a:ln><a:noFill/></a:ln></p:spPr><p:txBody><a:bodyPr anchorCtr="0" anchor="t" bIns="91425" lIns="91425" spcFirstLastPara="1" rIns="91425" wrap="square" tIns="91425"><a:noAutofit/></a:bodyPr><a:lstStyle/><a:p><a:pPr indent="0" lvl="0" marL="0" rtl="0" algn="ctr"><a:spcBef><a:spcPts val="0"/></a:spcBef><a:spcAft><a:spcPts val="0"/></a:spcAft><a:buNone/></a:pPr><a:r><a:rPr lang="en" sz="3000"><a:solidFill><a:srgbClr val="EFEFEF"/></a:solidFill><a:latin typeface="Special Elite"/><a:ea typeface="Special Elite"/><a:cs typeface="Special Elite"/><a:sym typeface="Special Elite"/></a:rPr><a:t>Ideological </a:t></a:r><a:r><a:rPr lang="en" sz="3000"><a:solidFill><a:srgbClr val="F4CCCC"/></a:solidFill><a:latin typeface="Special Elite"/><a:ea typeface="Special Elite"/><a:cs typeface="Special Elite"/><a:sym typeface="Special Elite"/></a:rPr><a:t>Warfare </a:t></a:r><a:endParaRPr sz="3000"><a:solidFill><a:srgbClr val="F4CCCC"/></a:solidFill><a:latin typeface="Special Elite"/><a:ea typeface="Special Elite"/><a:cs typeface="Special Elite"/><a:sym typeface="Special Elite"/></a:endParaRPr></a:p></p:txBody></p:sp><p:sp><p:nvSpPr><p:cNvPr id="478" name="Google Shape;478;p79"/><p:cNvSpPr txBox="1"/><p:nvPr/></p:nvSpPr><p:spPr><a:xfrm><a:off x="0" y="4130750"/><a:ext cx="4659000" cy="1030200"/></a:xfrm><a:prstGeom prst="rect"><a:avLst/></a:prstGeom><a:noFill/><a:ln><a:noFill/></a:ln></p:spPr><p:txBody><a:bodyPr anchorCtr="0" anchor="ctr" bIns="91425" lIns="91425" spcFirstLastPara="1" rIns="91425" wrap="square" tIns="91425"><a:noAutofit/></a:bodyPr><a:lstStyle/><a:p><a:pPr indent="0" lvl="0" marL="0" rtl="0" algn="ctr"><a:spcBef><a:spcPts val="0"/></a:spcBef><a:spcAft><a:spcPts val="0"/></a:spcAft><a:buNone/></a:pPr><a:r><a:rPr lang="en" sz="1600"><a:solidFill><a:srgbClr val="E14D43"/></a:solidFill><a:latin typeface="Open Sans"/><a:ea typeface="Open Sans"/><a:cs typeface="Open Sans"/><a:sym typeface="Open Sans"/></a:rPr><a:t>Anti-Hindu </a:t></a:r><a:r><a:rPr lang="en" sz="1600"><a:solidFill><a:srgbClr val="F3F3F3"/></a:solidFill><a:latin typeface="Open Sans"/><a:ea typeface="Open Sans"/><a:cs typeface="Open Sans"/><a:sym typeface="Open Sans"/></a:rPr><a:t>media mafia only spreads false propaganda and hate speech against </a:t></a:r><a:r><a:rPr lang="en" sz="1600"><a:solidFill><a:srgbClr val="F3F3F3"/></a:solidFill><a:latin typeface="Open Sans"/><a:ea typeface="Open Sans"/><a:cs typeface="Open Sans"/><a:sym typeface="Open Sans"/></a:rPr><a:t>HDH Nithyananda Paramashivam</a:t></a:r><a:r><a:rPr lang="en" sz="1600"><a:solidFill><a:srgbClr val="F3F3F3"/></a:solidFill><a:latin typeface="Open Sans"/><a:ea typeface="Open Sans"/><a:cs typeface="Open Sans"/><a:sym typeface="Open Sans"/></a:rPr><a:t>. </a:t></a:r><a:endParaRPr sz="1600"><a:solidFill><a:srgbClr val="F1C232"/></a:solidFill><a:latin typeface="Open Sans"/><a:ea typeface="Open Sans"/><a:cs typeface="Open Sans"/><a:sym typeface="Open Sans"/></a:endParaRPr></a:p></p:txBody></p:sp><p:pic><p:nvPicPr><p:cNvPr id="479" name="Google Shape;479;p79"/><p:cNvPicPr preferRelativeResize="0"/><p:nvPr/></p:nvPicPr><p:blipFill rotWithShape="1"><a:blip r:embed="rId3"><a:alphaModFix/></a:blip><a:srcRect b="2162" l="0" r="0" t="0"/><a:stretch/></p:blipFill><p:spPr><a:xfrm><a:off x="100" y="625775"/><a:ext cx="4659000" cy="3580199"/></a:xfrm><a:prstGeom prst="rect"><a:avLst/></a:prstGeom><a:noFill/><a:ln><a:noFill/></a:ln></p:spPr></p:pic><p:grpSp><p:nvGrpSpPr><p:cNvPr id="480" name="Google Shape;480;p79"/><p:cNvGrpSpPr/><p:nvPr/></p:nvGrpSpPr><p:grpSpPr><a:xfrm><a:off x="4715718" y="898345"/><a:ext cx="4444257" cy="2604452"/><a:chOff x="4715782" y="685050"/><a:chExt cx="4444257" cy="4456625"/></a:xfrm></p:grpSpPr><p:grpSp><p:nvGrpSpPr><p:cNvPr id="481" name="Google Shape;481;p79"/><p:cNvGrpSpPr/><p:nvPr/></p:nvGrpSpPr><p:grpSpPr><a:xfrm><a:off x="4715782" y="685050"/><a:ext cx="4422107" cy="4352238"/><a:chOff x="4715775" y="759762"/><a:chExt cx="4422107" cy="4575042"/></a:xfrm></p:grpSpPr><p:grpSp><p:nvGrpSpPr><p:cNvPr id="482" name="Google Shape;482;p79"/><p:cNvGrpSpPr/><p:nvPr/></p:nvGrpSpPr><p:grpSpPr><a:xfrm><a:off x="5147777" y="759762"/><a:ext cx="3990105" cy="4383941"/><a:chOff x="4940025" y="654522"/><a:chExt cx="4197901" cy="4565178"/></a:xfrm></p:grpSpPr><p:pic><p:nvPicPr><p:cNvPr id="483" name="Google Shape;483;p79"/><p:cNvPicPr preferRelativeResize="0"/><p:nvPr/></p:nvPicPr><p:blipFill><a:blip r:embed="rId4"><a:alphaModFix/></a:blip><a:stretch><a:fillRect/></a:stretch></p:blipFill><p:spPr><a:xfrm><a:off x="4940025" y="737925"/><a:ext cx="4197901" cy="4481775"/></a:xfrm><a:prstGeom prst="rect"><a:avLst/></a:prstGeom><a:noFill/><a:ln><a:noFill/></a:ln></p:spPr></p:pic><p:sp><p:nvSpPr><p:cNvPr id="484" name="Google Shape;484;p79"/><p:cNvSpPr txBox="1"/><p:nvPr/></p:nvSpPr><p:spPr><a:xfrm><a:off x="4963806" y="654522"/><a:ext cx="1184400" cy="343800"/></a:xfrm><a:prstGeom prst="rect"><a:avLst/></a:prstGeom><a:noFill/><a:ln><a:noFill/></a:ln></p:spPr><p:txBody><a:bodyPr anchorCtr="0" anchor="ctr" bIns="91425" lIns="91425" spcFirstLastPara="1" rIns="91425" wrap="square" tIns="91425"><a:noAutofit/></a:bodyPr><a:lstStyle/><a:p><a:pPr indent="0" lvl="0" marL="0" rtl="0" algn="ctr"><a:spcBef><a:spcPts val="0"/></a:spcBef><a:spcAft><a:spcPts val="0"/></a:spcAft><a:buNone/></a:pPr><a:r><a:rPr lang="en"><a:solidFill><a:srgbClr val="666666"/></a:solidFill><a:latin typeface="Open Sans"/><a:ea typeface="Open Sans"/><a:cs typeface="Open Sans"/><a:sym typeface="Open Sans"/></a:rPr><a:t>1200 ng/dL</a:t></a:r><a:endParaRPr><a:solidFill><a:srgbClr val="666666"/></a:solidFill><a:latin typeface="Open Sans"/><a:ea typeface="Open Sans"/><a:cs typeface="Open Sans"/><a:sym typeface="Open Sans"/></a:endParaRPr></a:p></p:txBody></p:sp><p:sp><p:nvSpPr><p:cNvPr id="485" name="Google Shape;485;p79"/><p:cNvSpPr txBox="1"/><p:nvPr/></p:nvSpPr><p:spPr><a:xfrm><a:off x="5934546" y="3353657"/><a:ext cx="1112100" cy="343800"/></a:xfrm><a:prstGeom prst="rect"><a:avLst/></a:prstGeom><a:noFill/><a:ln><a:noFill/></a:ln></p:spPr><p:txBody><a:bodyPr anchorCtr="0" anchor="ctr" bIns="91425" lIns="91425" spcFirstLastPara="1" rIns="91425" wrap="square" tIns="91425"><a:noAutofit/></a:bodyPr><a:lstStyle/><a:p><a:pPr indent="0" lvl="0" marL="0" rtl="0" algn="ctr"><a:spcBef><a:spcPts val="0"/></a:spcBef><a:spcAft><a:spcPts val="0"/></a:spcAft><a:buNone/></a:pPr><a:r><a:rPr lang="en"><a:solidFill><a:srgbClr val="666666"/></a:solidFill><a:latin typeface="Open Sans"/><a:ea typeface="Open Sans"/><a:cs typeface="Open Sans"/><a:sym typeface="Open Sans"/></a:rPr><a:t>400 ng/dL</a:t></a:r><a:endParaRPr><a:solidFill><a:srgbClr val="666666"/></a:solidFill><a:latin typeface="Open Sans"/><a:ea typeface="Open Sans"/><a:cs typeface="Open Sans"/><a:sym typeface="Open Sans"/></a:endParaRPr></a:p></p:txBody></p:sp><p:sp><p:nvSpPr><p:cNvPr id="486" name="Google Shape;486;p79"/><p:cNvSpPr txBox="1"/><p:nvPr/></p:nvSpPr><p:spPr><a:xfrm><a:off x="6820225" y="4552400"/><a:ext cx="1211700" cy="343800"/></a:xfrm><a:prstGeom prst="rect"><a:avLst/></a:prstGeom><a:noFill/><a:ln><a:noFill/></a:ln></p:spPr><p:txBody><a:bodyPr anchorCtr="0" anchor="ctr" bIns="91425" lIns="91425" spcFirstLastPara="1" rIns="91425" wrap="square" tIns="91425"><a:noAutofit/></a:bodyPr><a:lstStyle/><a:p><a:pPr indent="0" lvl="0" marL="0" rtl="0" algn="ctr"><a:spcBef><a:spcPts val="0"/></a:spcBef><a:spcAft><a:spcPts val="0"/></a:spcAft><a:buNone/></a:pPr><a:r><a:rPr lang="en"><a:solidFill><a:srgbClr val="666666"/></a:solidFill><a:latin typeface="Open Sans"/><a:ea typeface="Open Sans"/><a:cs typeface="Open Sans"/><a:sym typeface="Open Sans"/></a:rPr><a:t>80 ng/dL</a:t></a:r><a:endParaRPr><a:solidFill><a:srgbClr val="666666"/></a:solidFill><a:latin typeface="Open Sans"/><a:ea typeface="Open Sans"/><a:cs typeface="Open Sans"/><a:sym typeface="Open Sans"/></a:endParaRPr></a:p></p:txBody></p:sp><p:sp><p:nvSpPr><p:cNvPr id="487" name="Google Shape;487;p79"/><p:cNvSpPr txBox="1"/><p:nvPr/></p:nvSpPr><p:spPr><a:xfrm><a:off x="7781984" y="4764184"/><a:ext cx="1211700" cy="287400"/></a:xfrm><a:prstGeom prst="rect"><a:avLst/></a:prstGeom><a:noFill/><a:ln><a:noFill/></a:ln></p:spPr><p:txBody><a:bodyPr anchorCtr="0" anchor="ctr" bIns="91425" lIns="91425" spcFirstLastPara="1" rIns="91425" wrap="square" tIns="91425"><a:noAutofit/></a:bodyPr><a:lstStyle/><a:p><a:pPr indent="0" lvl="0" marL="0" rtl="0" algn="ctr"><a:spcBef><a:spcPts val="0"/></a:spcBef><a:spcAft><a:spcPts val="0"/></a:spcAft><a:buNone/></a:pPr><a:r><a:rPr lang="en"><a:solidFill><a:srgbClr val="666666"/></a:solidFill><a:latin typeface="Open Sans"/><a:ea typeface="Open Sans"/><a:cs typeface="Open Sans"/><a:sym typeface="Open Sans"/></a:rPr><a:t>12 ng/dL</a:t></a:r><a:endParaRPr><a:solidFill><a:srgbClr val="666666"/></a:solidFill><a:latin typeface="Open Sans"/><a:ea typeface="Open Sans"/><a:cs typeface="Open Sans"/><a:sym typeface="Open Sans"/></a:endParaRPr></a:p></p:txBody></p:sp></p:grpSp><p:sp><p:nvSpPr><p:cNvPr id="488" name="Google Shape;488;p79"/><p:cNvSpPr txBox="1"/><p:nvPr/></p:nvSpPr><p:spPr><a:xfrm rot="-5400000"><a:off x="3188025" y="3222655"/><a:ext cx="3639900" cy="584400"/></a:xfrm><a:prstGeom prst="rect"><a:avLst/></a:prstGeom><a:noFill/><a:ln><a:noFill/></a:ln></p:spPr><p:txBody><a:bodyPr anchorCtr="0" anchor="t" bIns="91425" lIns="91425" spcFirstLastPara="1" rIns="91425" wrap="square" tIns="91425"><a:noAutofit/></a:bodyPr><a:lstStyle/><a:p><a:pPr indent="0" lvl="0" marL="0" rtl="0" algn="ctr"><a:spcBef><a:spcPts val="0"/></a:spcBef><a:spcAft><a:spcPts val="0"/></a:spcAft><a:buNone/></a:pPr><a:r><a:rPr lang="en"><a:latin typeface="Open Sans"/><a:ea typeface="Open Sans"/><a:cs typeface="Open Sans"/><a:sym typeface="Open Sans"/></a:rPr><a:t>TESTOSTERONE</a:t></a:r><a:br><a:rPr lang="en"><a:latin typeface="Open Sans"/><a:ea typeface="Open Sans"/><a:cs typeface="Open Sans"/><a:sym typeface="Open Sans"/></a:rPr></a:br><a:r><a:rPr lang="en"><a:latin typeface="Open Sans"/><a:ea typeface="Open Sans"/><a:cs typeface="Open Sans"/><a:sym typeface="Open Sans"/></a:rPr><a:t>LEVEL</a:t></a:r><a:endParaRPr><a:latin typeface="Open Sans"/><a:ea typeface="Open Sans"/><a:cs typeface="Open Sans"/><a:sym typeface="Open Sans"/></a:endParaRPr></a:p></p:txBody></p:sp><p:cxnSp><p:nvCxnSpPr><p:cNvPr id="489" name="Google Shape;489;p79"/><p:cNvCxnSpPr/><p:nvPr/></p:nvCxnSpPr><p:spPr><a:xfrm><a:off x="5242318" y="1141792"/><a:ext cx="2100" cy="3843000"/></a:xfrm><a:prstGeom prst="straightConnector1"><a:avLst/></a:prstGeom><a:noFill/><a:ln cap="flat" cmpd="sng" w="9525"><a:solidFill><a:schemeClr val="dk2"/></a:solidFill><a:prstDash val="solid"/><a:round/><a:headEnd len="med" w="med" type="none"/><a:tailEnd len="med" w="med" type="none"/></a:ln></p:spPr></p:cxnSp><p:cxnSp><p:nvCxnSpPr><p:cNvPr id="490" name="Google Shape;490;p79"/><p:cNvCxnSpPr/><p:nvPr/></p:nvCxnSpPr><p:spPr><a:xfrm rot="10800000"><a:off x="5242205" y="4982274"/><a:ext cx="3756000" cy="27900"/></a:xfrm><a:prstGeom prst="straightConnector1"><a:avLst/></a:prstGeom><a:noFill/><a:ln cap="flat" cmpd="sng" w="9525"><a:solidFill><a:schemeClr val="dk2"/></a:solidFill><a:prstDash val="solid"/><a:round/><a:headEnd len="med" w="med" type="none"/><a:tailEnd len="med" w="med" type="none"/></a:ln></p:spPr></p:cxnSp></p:grpSp><p:sp><p:nvSpPr><p:cNvPr id="491" name="Google Shape;491;p79"/><p:cNvSpPr txBox="1"/><p:nvPr/></p:nvSpPr><p:spPr><a:xfrm><a:off x="5233725" y="4643075"/><a:ext cx="976800" cy="498600"/></a:xfrm><a:prstGeom prst="rect"><a:avLst/></a:prstGeom><a:noFill/><a:ln><a:noFill/></a:ln></p:spPr><p:txBody><a:bodyPr anchorCtr="0" anchor="t" bIns="91425" lIns="91425" spcFirstLastPara="1" rIns="91425" wrap="square" tIns="91425"><a:noAutofit/></a:bodyPr><a:lstStyle/><a:p><a:pPr indent="0" lvl="0" marL="0" rtl="0" algn="ctr"><a:spcBef><a:spcPts val="0"/></a:spcBef><a:spcAft><a:spcPts val="0"/></a:spcAft><a:buNone/></a:pPr><a:r><a:rPr lang="en" sz="1200"><a:latin typeface="Open Sans"/><a:ea typeface="Open Sans"/><a:cs typeface="Open Sans"/><a:sym typeface="Open Sans"/></a:rPr><a:t>Normal Adult Male</a:t></a:r><a:endParaRPr sz="1200"><a:latin typeface="Open Sans"/><a:ea typeface="Open Sans"/><a:cs typeface="Open Sans"/><a:sym typeface="Open Sans"/></a:endParaRPr></a:p></p:txBody></p:sp><p:sp><p:nvSpPr><p:cNvPr id="492" name="Google Shape;492;p79"/><p:cNvSpPr txBox="1"/><p:nvPr/></p:nvSpPr><p:spPr><a:xfrm><a:off x="6153300" y="4643050"/><a:ext cx="936600" cy="498600"/></a:xfrm><a:prstGeom prst="rect"><a:avLst/></a:prstGeom><a:noFill/><a:ln><a:noFill/></a:ln></p:spPr><p:txBody><a:bodyPr anchorCtr="0" anchor="t" bIns="91425" lIns="91425" spcFirstLastPara="1" rIns="91425" wrap="square" tIns="91425"><a:noAutofit/></a:bodyPr><a:lstStyle/><a:p><a:pPr indent="0" lvl="0" marL="0" rtl="0" algn="ctr"><a:spcBef><a:spcPts val="0"/></a:spcBef><a:spcAft><a:spcPts val="0"/></a:spcAft><a:buNone/></a:pPr><a:r><a:rPr lang="en" sz="1200"><a:latin typeface="Open Sans"/><a:ea typeface="Open Sans"/><a:cs typeface="Open Sans"/><a:sym typeface="Open Sans"/></a:rPr><a:t>New born male</a:t></a:r><a:endParaRPr sz="1200"><a:latin typeface="Open Sans"/><a:ea typeface="Open Sans"/><a:cs typeface="Open Sans"/><a:sym typeface="Open Sans"/></a:endParaRPr></a:p></p:txBody></p:sp><p:sp><p:nvSpPr><p:cNvPr id="493" name="Google Shape;493;p79"/><p:cNvSpPr txBox="1"/><p:nvPr/></p:nvSpPr><p:spPr><a:xfrm><a:off x="6991500" y="4719250"/><a:ext cx="936600" cy="315600"/></a:xfrm><a:prstGeom prst="rect"><a:avLst/></a:prstGeom><a:noFill/><a:ln><a:noFill/></a:ln></p:spPr><p:txBody><a:bodyPr anchorCtr="0" anchor="t" bIns="91425" lIns="91425" spcFirstLastPara="1" rIns="91425" wrap="square" tIns="91425"><a:noAutofit/></a:bodyPr><a:lstStyle/><a:p><a:pPr indent="0" lvl="0" marL="0" rtl="0" algn="ctr"><a:spcBef><a:spcPts val="0"/></a:spcBef><a:spcAft><a:spcPts val="0"/></a:spcAft><a:buNone/></a:pPr><a:r><a:rPr lang="en" sz="1200"><a:latin typeface="Open Sans"/><a:ea typeface="Open Sans"/><a:cs typeface="Open Sans"/><a:sym typeface="Open Sans"/></a:rPr><a:t>Female</a:t></a:r><a:endParaRPr sz="1200"><a:latin typeface="Open Sans"/><a:ea typeface="Open Sans"/><a:cs typeface="Open Sans"/><a:sym typeface="Open Sans"/></a:endParaRPr></a:p></p:txBody></p:sp><p:sp><p:nvSpPr><p:cNvPr id="494" name="Google Shape;494;p79"/><p:cNvSpPr txBox="1"/><p:nvPr/></p:nvSpPr><p:spPr><a:xfrm><a:off x="7704739" y="4643050"/><a:ext cx="1455300" cy="424800"/></a:xfrm><a:prstGeom prst="rect"><a:avLst/></a:prstGeom><a:noFill/><a:ln><a:noFill/></a:ln></p:spPr><p:txBody><a:bodyPr anchorCtr="0" anchor="t" bIns="91425" lIns="91425" spcFirstLastPara="1" rIns="91425" wrap="square" tIns="91425"><a:noAutofit/></a:bodyPr><a:lstStyle/><a:p><a:pPr indent="0" lvl="0" marL="0" rtl="0" algn="ctr"><a:spcBef><a:spcPts val="0"/></a:spcBef><a:spcAft><a:spcPts val="0"/></a:spcAft><a:buNone/></a:pPr><a:r><a:rPr b="1" lang="en" sz="1100"><a:latin typeface="Open Sans"/><a:ea typeface="Open Sans"/><a:cs typeface="Open Sans"/><a:sym typeface="Open Sans"/></a:rPr><a:t>HDH </a:t></a:r><a:r><a:rPr b="1" lang="en" sz="1100"><a:latin typeface="Open Sans"/><a:ea typeface="Open Sans"/><a:cs typeface="Open Sans"/><a:sym typeface="Open Sans"/></a:rPr><a:t>Nithyananda</a:t></a:r><a:endParaRPr b="1" sz="1100"><a:latin typeface="Open Sans"/><a:ea typeface="Open Sans"/><a:cs typeface="Open Sans"/><a:sym typeface="Open Sans"/></a:endParaRPr></a:p><a:p><a:pPr indent="0" lvl="0" marL="0" rtl="0" algn="ctr"><a:spcBef><a:spcPts val="0"/></a:spcBef><a:spcAft><a:spcPts val="0"/></a:spcAft><a:buNone/></a:pPr><a:r><a:rPr b="1" lang="en" sz="1100"><a:latin typeface="Open Sans"/><a:ea typeface="Open Sans"/><a:cs typeface="Open Sans"/><a:sym typeface="Open Sans"/></a:rPr><a:t>Paramashivam</a:t></a:r><a:endParaRPr b="1" sz="1100"><a:latin typeface="Open Sans"/><a:ea typeface="Open Sans"/><a:cs typeface="Open Sans"/><a:sym typeface="Open Sans"/></a:endParaRPr></a:p></p:txBody></p:sp></p:grpSp><p:sp><p:nvSpPr><p:cNvPr id="495" name="Google Shape;495;p79"/><p:cNvSpPr/><p:nvPr/></p:nvSpPr><p:spPr><a:xfrm><a:off x="5294925" y="3687875"/><a:ext cx="3816900" cy="442800"/></a:xfrm><a:prstGeom prst="roundRect"><a:avLst><a:gd fmla="val 20663" name="adj"/></a:avLst></a:prstGeom><a:solidFill><a:schemeClr val="lt2"/></a:solidFill><a:ln cap="flat" cmpd="sng" w="9525"><a:solidFill><a:schemeClr val="dk2"/></a:solidFill><a:prstDash val="solid"/><a:round/><a:headEnd len="sm" w="sm" type="none"/><a:tailEnd len="sm" w="sm" type="none"/></a:ln></p:spPr><p:txBody><a:bodyPr anchorCtr="0" anchor="ctr" bIns="91425" lIns="91425" spcFirstLastPara="1" rIns="91425" wrap="square" tIns="91425"><a:noAutofit/></a:bodyPr><a:lstStyle/><a:p><a:pPr indent="0" lvl="0" marL="0" rtl="0" algn="ctr"><a:spcBef><a:spcPts val="0"/></a:spcBef><a:spcAft><a:spcPts val="0"/></a:spcAft><a:buNone/></a:pPr><a:r><a:rPr lang="en"><a:solidFill><a:srgbClr val="B45F06"/></a:solidFill><a:latin typeface="Open Sans"/><a:ea typeface="Open Sans"/><a:cs typeface="Open Sans"/><a:sym typeface="Open Sans"/></a:rPr><a:t>Medical science ratifies enlightened physiology of Ardhanarishwara.</a:t></a:r><a:endParaRPr/></a:p></p:txBody></p:sp><p:sp><p:nvSpPr><p:cNvPr id="496" name="Google Shape;496;p79"/><p:cNvSpPr txBox="1"/><p:nvPr><p:ph idx="4294967295" type="ctrTitle"/></p:nvPr></p:nvSpPr><p:spPr><a:xfrm><a:off x="4659100" y="50"/><a:ext cx="4485000" cy="738600"/></a:xfrm><a:prstGeom prst="rect"><a:avLst/></a:prstGeom><a:noFill/></p:spPr><p:txBody><a:bodyPr anchorCtr="0" anchor="t" bIns="91425" lIns="91425" spcFirstLastPara="1" rIns="91425" wrap="square" tIns="91425"><a:noAutofit/></a:bodyPr><a:lstStyle/><a:p><a:pPr indent="0" lvl="0" marL="0" rtl="0" algn="l"><a:spcBef><a:spcPts val="0"/></a:spcBef><a:spcAft><a:spcPts val="0"/></a:spcAft><a:buNone/></a:pPr><a:r><a:rPr lang="en" sz="4800"><a:solidFill><a:srgbClr val="F1C232"/></a:solidFill><a:latin typeface="Great Vibes"/><a:ea typeface="Great Vibes"/><a:cs typeface="Great Vibes"/><a:sym typeface="Great Vibes"/></a:rPr><a:t>Satya </a:t></a:r><a:r><a:rPr lang="en" sz="2800"><a:solidFill><a:srgbClr val="F1C232"/></a:solidFill><a:latin typeface="Great Vibes"/><a:ea typeface="Great Vibes"/><a:cs typeface="Great Vibes"/><a:sym typeface="Great Vibes"/></a:rPr><a:t>- Ultimate Truth</a:t></a:r><a:endParaRPr sz="3100"><a:latin typeface="Quicksand"/><a:ea typeface="Quicksand"/><a:cs typeface="Quicksand"/><a:sym typeface="Quicksand"/></a:endParaRPr></a:p></p:txBody></p:sp><p:sp><p:nvSpPr><p:cNvPr id="497" name="Google Shape;497;p79"/><p:cNvSpPr txBox="1"/><p:nvPr/></p:nvSpPr><p:spPr><a:xfrm><a:off x="101750" y="2000375"/><a:ext cx="2126100" cy="797700"/></a:xfrm><a:prstGeom prst="rect"><a:avLst/></a:prstGeom><a:solidFill><a:srgbClr val="000000"/></a:solidFill><a:ln><a:noFill/></a:ln></p:spPr><p:txBody><a:bodyPr anchorCtr="0" anchor="ctr" bIns="0" lIns="0" spcFirstLastPara="1" rIns="0" wrap="square" tIns="0"><a:noAutofit/></a:bodyPr><a:lstStyle/><a:p><a:pPr indent="0" lvl="0" marL="0" rtl="0" algn="ctr"><a:spcBef><a:spcPts val="0"/></a:spcBef><a:spcAft><a:spcPts val="0"/></a:spcAft><a:buNone/></a:pPr><a:r><a:rPr lang="en" sz="1100"><a:solidFill><a:srgbClr val="F4CCCC"/></a:solidFill><a:latin typeface="Fira Sans"/><a:ea typeface="Fira Sans"/><a:cs typeface="Fira Sans"/><a:sym typeface="Fira Sans"/></a:rPr><a:t>False accusations were made on </a:t></a:r><a:r><a:rPr lang="en" sz="1000"><a:solidFill><a:srgbClr val="F4CCCC"/></a:solidFill><a:latin typeface="Fira Sans"/><a:ea typeface="Fira Sans"/><a:cs typeface="Fira Sans"/><a:sym typeface="Fira Sans"/></a:rPr><a:t>HDH Nithyananda Paramashivam,</a:t></a:r><a:r><a:rPr lang="en" sz="1100"><a:solidFill><a:srgbClr val="F4CCCC"/></a:solidFill><a:latin typeface="Fira Sans"/><a:ea typeface="Fira Sans"/><a:cs typeface="Fira Sans"/><a:sym typeface="Fira Sans"/></a:rPr><a:t> for which media aired 14,000 hours of hate speech.</a:t></a:r><a:endParaRPr sz="1100"><a:solidFill><a:srgbClr val="F4CCCC"/></a:solidFill><a:latin typeface="Fira Sans"/><a:ea typeface="Fira Sans"/><a:cs typeface="Fira Sans"/><a:sym typeface="Fira Sans"/></a:endParaRPr></a:p></p:txBody></p:sp><p:sp><p:nvSpPr><p:cNvPr id="498" name="Google Shape;498;p79"/><p:cNvSpPr txBox="1"/><p:nvPr/></p:nvSpPr><p:spPr><a:xfrm><a:off x="2276000" y="2000375"/><a:ext cx="2285100" cy="797700"/></a:xfrm><a:prstGeom prst="rect"><a:avLst/></a:prstGeom><a:solidFill><a:srgbClr val="000000"/></a:solidFill><a:ln><a:noFill/></a:ln></p:spPr><p:txBody><a:bodyPr anchorCtr="0" anchor="ctr" bIns="0" lIns="0" spcFirstLastPara="1" rIns="0" wrap="square" tIns="0"><a:noAutofit/></a:bodyPr><a:lstStyle/><a:p><a:pPr indent="0" lvl="0" marL="0" rtl="0" algn="ctr"><a:spcBef><a:spcPts val="0"/></a:spcBef><a:spcAft><a:spcPts val="0"/></a:spcAft><a:buNone/></a:pPr><a:r><a:rPr lang="en" sz="1200"><a:solidFill><a:srgbClr val="FFD966"/></a:solidFill><a:latin typeface="Fira Sans"/><a:ea typeface="Fira Sans"/><a:cs typeface="Fira Sans"/><a:sym typeface="Fira Sans"/></a:rPr><a:t>HDH Nithyananda Paramashivam establishes 3 Guinness World records; Indian media gave not even 1 minute news coverage.</a:t></a:r><a:endParaRPr><a:solidFill><a:srgbClr val="FFD966"/></a:solidFill><a:latin typeface="Fira Sans"/><a:ea typeface="Fira Sans"/><a:cs typeface="Fira Sans"/><a:sym typeface="Fira Sans"/></a:endParaRPr></a:p></p:txBody></p:sp><p:sp><p:nvSpPr><p:cNvPr id="499" name="Google Shape;499;p79"/><p:cNvSpPr txBox="1"/><p:nvPr/></p:nvSpPr><p:spPr><a:xfrm><a:off x="209700" y="2798075"/><a:ext cx="4444200" cy="1332600"/></a:xfrm><a:prstGeom prst="rect"><a:avLst/></a:prstGeom><a:solidFill><a:srgbClr val="000000"/></a:solidFill><a:ln><a:noFill/></a:ln></p:spPr><p:txBody><a:bodyPr anchorCtr="0" anchor="ctr" bIns="0" lIns="0" spcFirstLastPara="1" rIns="0" wrap="square" tIns="0"><a:noAutofit/></a:bodyPr><a:lstStyle/><a:p><a:pPr indent="0" lvl="0" marL="0" rtl="0" algn="ctr"><a:spcBef><a:spcPts val="0"/></a:spcBef><a:spcAft><a:spcPts val="0"/></a:spcAft><a:buNone/></a:pPr><a:r><a:rPr lang="en"><a:solidFill><a:srgbClr val="FFFFFF"/></a:solidFill><a:latin typeface="Fira Sans"/><a:ea typeface="Fira Sans"/><a:cs typeface="Fira Sans"/><a:sym typeface="Fira Sans"/></a:rPr><a:t>Anti-Hindu terrorist elements who attacked HDH through character assassination, lawfare, hate propaganda, were penalized by various Courts in USA and India. The total penalty charged to the anti-Hindu elements is more than 40 crore INR. </a:t></a:r><a:endParaRPr><a:solidFill><a:srgbClr val="FFFFFF"/></a:solidFill><a:latin typeface="Fira Sans"/><a:ea typeface="Fira Sans"/><a:cs typeface="Fira Sans"/><a:sym typeface="Fira Sans"/></a:endParaRPr></a:p></p:txBody></p:sp><p:sp><p:nvSpPr><p:cNvPr id="500" name="Google Shape;500;p79"/><p:cNvSpPr txBox="1"/><p:nvPr/></p:nvSpPr><p:spPr><a:xfrm><a:off x="4640400" y="4130675"/><a:ext cx="4485000" cy="1030200"/></a:xfrm><a:prstGeom prst="rect"><a:avLst/></a:prstGeom><a:noFill/><a:ln><a:noFill/></a:ln></p:spPr><p:txBody><a:bodyPr anchorCtr="0" anchor="b" bIns="0" lIns="91425" spcFirstLastPara="1" rIns="91425" wrap="square" tIns="0"><a:noAutofit/></a:bodyPr><a:lstStyle/><a:p><a:pPr indent="0" lvl="0" marL="0" rtl="0" algn="ctr"><a:spcBef><a:spcPts val="0"/></a:spcBef><a:spcAft><a:spcPts val="0"/></a:spcAft><a:buNone/></a:pPr><a:r><a:rPr lang="en" sz="1300"><a:solidFill><a:srgbClr val="434343"/></a:solidFill><a:latin typeface="Open Sans"/><a:ea typeface="Open Sans"/><a:cs typeface="Open Sans"/><a:sym typeface="Open Sans"/></a:rPr><a:t>State Police knew HDH Nithyananda Paramashivam was impotent, from the reports of the potency test they did in 2010. They did it again in 2014. The test involved injected lethal chemicals. A Policeman openly told media that he might be arrested if HDH died.</a:t></a:r><a:endParaRPr sz="1300"><a:solidFill><a:srgbClr val="434343"/></a:solidFill><a:latin typeface="Open Sans"/><a:ea typeface="Open Sans"/><a:cs typeface="Open Sans"/><a:sym typeface="Open Sans"/></a:endParaRPr></a:p></p:txBody></p:sp></p:spTree></p:cSld><p:clrMapOvr><a:masterClrMapping/></p:clrMapOvr></p:sld>